judah/__init__.py
judah/controllers/__init__.py
judah/controllers/base/__init__.py
judah/controllers/base/date_based.py
judah/controllers/base/quarter_based.py
judah/controllers/db_to_db/__init__.py
judah/controllers/export_site_to_db/__init__.py
judah/controllers/export_site_to_db/date_based.py
judah/controllers/export_site_to_db/index_based.py
judah/controllers/export_site_to_db/quarter_based.py
judah/controllers/rest_api_to_db/__init__.py
judah/destinations/__init__.py
judah/destinations/base.py
judah/destinations/database/__init__.py
judah/destinations/database/config.py
judah/destinations/database/connection.py
judah/destinations/database/model.py
judah/sources/__init__.py
judah/sources/base/__init__.py
judah/sources/base/date_based.py
judah/sources/base/quarter_based.py
judah/sources/database/__init__.py
judah/sources/database/config.py
judah/sources/database/date_based.py
judah/sources/export_site/__init__.py
judah/sources/export_site/date_based.py
judah/sources/export_site/index_based.py
judah/sources/export_site/quarter_based.py
judah/sources/rest_api/__init__.py
judah/sources/rest_api/date_based.py
judah/transformers/__init__.py
judah/transformers/base.py
judah/transformers/datetime_transformer.py
judah/transformers/empty_string_transformer.py
judah/transformers/field_name_alias_transformer.py
judah/transformers/field_name_cleaner_transformer.py
judah/transformers/field_value_alias_transformer.py
judah/utils/__init__.py
judah/utils/assets.py
judah/utils/cron.py
judah/utils/data.py
judah/utils/dates.py
judah/utils/logging.py
judah/utils/selenium.py
judah/utils/testing.py
test/test_controllers/__init__.py
test/test_controllers/test_date_based.py
test/test_controllers/test_quarter_based.py
test/test_destinations/__init__.py
test/test_destinations/test_database/__init__.py
test/test_destinations/test_database/test_connection.py
test/test_destinations/test_database/test_model.py
test/test_sources/__init__.py
test/test_sources/test_database/__init__.py
judah-0.0.6.dist-info/LICENSE
judah-0.0.6.dist-info/METADATA
judah-0.0.6.dist-info/WHEEL
judah-0.0.6.dist-info/top_level.txt
judah-0.0.6.dist-info/RECORD
