Metadata-Version: 2.1
Name: judah
Version: 0.0.6
Summary: A simple service-oriented ETL framework for integrations
Home-page: https://github.com/sopherapps/judah
Author: Martin Ahindura
Author-email: team.sopherapps@gmail.com
License: MIT
Platform: UNKNOWN
Classifier: License :: OSI Approved :: MIT License
Classifier: Programming Language :: Python :: 3
Classifier: Programming Language :: Python :: 3.6
Requires-Dist: pydantic
Requires-Dist: python-dotenv
Requires-Dist: email-notifier
Requires-Dist: psycopg2-binary
Requires-Dist: selenium
Requires-Dist: requests
Requires-Dist: SQLAlchemy
Requires-Dist: xml-stream
Requires-Dist: webdriver-manager
Requires-Dist: bonobo
Requires-Dist: xlrd
